Workbook

Sheet Append1
A1: Column1 | B1: Column3
A2: Revenue | B2: 547118754
A3: Cost of sales | B3: -329945347
A4: Gross profit | B4: 217173407
A5: Other Income | B5: 0
A6: Marketing and distribution expenses | B6: -73779995
A7: Administrative expenses | B7: -20089038
A8: (Write back)/ impairment of financial assets | B8: 483222
A9: Results from operating activities | B9: 123787596
A10: Finance income | B10: 5690939
A11: Finance costs | B11: -233503964
A12: Net finance costs | B12: -227813025
A13: (Loss)/profit before income tax | B13: -104025429
... A15: (Loss)/profit for the year | B15: -79473781
A16: Total comprehensive (loss)/income for the year | B16: 48,965,488
A17: (Loss)/profit for the year is attributable to:
A18: Owners of the company | B18: 48,965,488
A19: (Loss)/earnings per share | B19: N
A20: Basic (loss)/earnings per share | B20: 61.77
A21: Diluted (loss)/earnings per share | B21: 61.77

Sheet Table034 (Page 26) (2)
A1: Column1 | B1: Column2 | C1: Column3
A2: Total comprehensive (loss)/income for the year | B2: (79,473,781) | C2: 48,965,488
A3: (Loss)/profit for the year is attributable to:
A4: Owners of the company | B4: (79,473,781) | C4: 48,965,488
A5: (Loss)/earnings per share | B5: N | C5: N
A6: Basic (loss)/earnings per share | B6: (100.26) | C6: 61.77
A7: Diluted (loss)/earnings per share | B7: (100.26) | C7: 61.77

Sheet Table033 (Page 26) (2)
A1: Column1 | B1: Column2 | C1: Column3 | D1: Column4
A2: Revenue | B2: 9 | C2: 547118754 | D2: 446819260
A3: Cost of sales | B3: 11(c) | C3: -329945347 | D3: -291054270
A4: Gross profit | C4: 217173407 | D4: 155764990
A5: Marketing and distribution expenses | B5: 11(c) | C5: -73779995 | D5: -57331351
A6: Administrative expenses | B6: 11(c) | C6: -20089038 | D6: -10935972
A7: (Write back)/ impairment of financial assets | B7: 11 (b) | C7: 483222 | D7: -29043
A8: Results from operating activities | C8: 123787596 | D8: 87468624
A9: Finance income | B9: 10 | C9: 5690939 | D9: 4777113
A10: Finance costs | B10: 10 | C10: -233503964 | D10: -21136366
A11: Net finance costs | C11: -227813025 | D11: -16359253
A12: (Loss)/profit before income tax | C12: -104025429 | D12: 71109371
A13: Income tax credit/ (expense) | B13: 13 (a) | C13: 24551648 | D13: -22143883
A14: (Loss)/profit for the year | C14: -79473781 | D14: 48965488

Sheet Historical Variance Analysis
A1: Line Item (Figures in ₦ Billions) | B1: 2025 | C1: 2024 | D1: 2023 | E1: 2024 Var (Naira) | F1: 2024 Var (%) | G1: 2025 Var (Naira) | H1: 2025 Var (%)
A2: Revenue | B2: 1207773081 | C2: 958814739 | D2: =_xlfn.XLOOKUP(A2, Append1!A:A, Append1!B:B,0) -> 547118754 | E2: =C2-D2 -> 411695985 | F2: =E2/ABS(D2) -> 0.75248012 | G2: =B2-C2 -> 248958342 | H2: =G2/ABS(C2) -> 0.25965219
A3: Cost of sales | B3: -771881648 | C3: -652459896 | D3: =_xlfn.XLOOKUP(A3, Append1!A:A, Append1!B:B,0) -> -329945347 | E3: =C3-D3 -> -322514549 | F3: =E3/ABS(D3) -> -0.9774787 | G3: =B3-C3 -> -119421752 | H3: =G3/ABS(C3) -> -0.18303309
A4: Gross profit | B4: 435891433 | C4: 306354843 | D4: =_xlfn.XLOOKUP(A4, Append1!A:A, Append1!B:B,0) -> 217173407 | E4: =C4-D4 -> 89181436 | F4: =E4/ABS(D4) -> 0.41064621 | G4: =B4-C4 -> 129536590 | H4: =G4/ABS(C4) -> 0.42283187
A5: Gross profit Margin | B5: =B4/B2 -> 0.36090507 | C5: =C4/C2 -> 0.31951412 | D5: =D4/D2 -> 0.39694016 | H5: =G5/ABS(C5) -> 0
A6: Other income | B6: 1152207 | C6: 737107 | D6: 454436 | E6: =C6-D6 -> 282671 | F6: =E6/ABS(D6) -> 0.62202598 | G6: =B6-C6 -> 415100 | H6: =G6/ABS(C6) -> 0.56314755
A7: Marketing and distribution expenses | B7: -161694691 | C7: -106851671 | D7: =_xlfn.XLOOKUP(A7, Append1!A:A, Append1!B:B,0) -> -73779995 | E7: =C7-D7 -> -33071676 | F7: =E7/ABS(D7) -> -0.4482472 | G7: =B7-C7 -> -54843020 | H7: =G7/ABS(C7) -> -0.5132631
A8: Administrative expenses | B8: -49811090 | C8: -32529512 | D8: =_xlfn.XLOOKUP(A8, Append1!A:A, Append1!B:B,0) -> -20089038 | E8: =C8-D8 -> -12440474 | F8: =E8/ABS(D8) -> -0.61926679 | G8: =B8-C8 -> -17281578 | H8: =G8/ABS(C8) -> -0.53125845
A9: Impairment (loss) /write-back on financial assets | B9: -155181 | C9: 165495 | D9: 483222 | E9: =C9-D9 -> -317727 | F9: =E9/ABS(D9) -> -0.65751766 | G9: =B9-C9 -> -320676 | H9: =G9/ABS(C9) -> -1.9376779
A10: Results from operating activities | B10: 225382678 | C10: 167876262 | D10: =_xlfn.XLOOKUP(A10, Append1!A:A, Append1!B:B,0) -> 123787596 | E10: =C10-D10 -> 44088666 | F10: =E10/ABS(D10) -> 0.35616384 | G10: =B10-C10 -> 57506416 | H10: =G10/ABS(C10) -> 0.3425524
A11: Operating Profit Margin | B11: =B10/B2 -> 0.18661012 | C11: =C10/C2 -> 0.17508728 | D11: =D10/D2 -> 0.22625362 | H11: =G11/ABS(C11) -> 0
A12: Finance income | B12: 42425284 | C12: 3367575 | D12: =_xlfn.XLOOKUP(A12, Append1!A:A, Append1!B:B,0) -> 5690939 | E12: =C12-D12 -> -2323364 | F12: =E12/ABS(D12) -> -0.4082567 | G12: =B12-C12 -> 39057709 | H12: =G12/ABS(C12) -> 11.59817
A13: Finance costs | B13: -100961184 | C13: -392832386 | D13: =_xlfn.XLOOKUP(A13, Append1!A:A, Append1!B:B,0) -> -233503964 | E13: =C13-D13 -> -159328422 | F13: =E13/ABS(D13) -> -0.68233712 | G13: =B13-C13 -> 291871202 | H13: =G13/ABS(C13) -> 0.7429917
A14: Net finance costs | B14: -58535900 | C14: -389464811 | D14: =_xlfn.XLOOKUP(A14, Append1!A:A, Append1!B:B,0) -> -227813025 | E14: =C14-D14 -> -161651786 | F14: =E14/ABS(D14) -> -0.70958096 | G14: =B14-C14 -> 330928911 | H14: =G14/ABS(C14) -> 0.8497017
A15: Profit /(loss) before income tax | B15: 166846778 | C15: -221588549 | D15: -104025429 | E15: =C15-D15 -> -117563120 | F15: =E15/ABS(D15) -> -1.1301383 | G15: =B15-C15 -> 388435327 | H15: =G15/ABS(C15) -> 1.7529576
A16: Income tax (expense) /credit | B16: 61880777 | C16: 56993527 | D16: 24551648 | E16: =C16-D16 -> 32441879 | F16: =E16/ABS(D16) -> 1.3213728 | G16: =B16-C16 -> 4887250 | H16: =G16/ABS(C16) -> 0.085750966
A17: Profit /(loss) for the year | B17: 104966001 | C17: -164595022 | D17: -79473781 | E17: =C17-D17 -> -85121241 | F17: =E17/ABS(D17) -> -1.0710607 | G17: =B17-C17 -> 269561023 | H17: =G17/ABS(C17) -> 1.6377228
A18: Net Profit Margin | B18: =B17/B2 -> 0.08690871 | C18: =C17/C2 -> -0.17166509 | D18: =D17/D2 -> -0.14525874
A19: Profit /(loss) for the year is attributable to:
A20: Owners of the Company | B20: 104966001 | C20: -164595022 | D20: -79473781 | E20: =C20-D20 -> -85121241 | F20: =E20/ABS(D20) -> -1.0710607 | G20: =B20-C20 -> 269561023 | H20: =G20/ABS(C20) -> 1.6377228
A21: Earnings /(loss) per share | B21: N | C21: N | D21: N
A22: Basic earnings /(loss) per share | B22: 132.42 | C22: -207.65 | D22: 61.77 | E22: =C22-D22 -> -269.42 | G22: =B22-C22 -> 340.07
A23: Diluted earnings /(loss) per share | B23: 132.42 | C23: -207.65 | D23: 61.77 | E23: =C23-D23 -> -269.42 | G23: =B23-C23 -> 340.07
A25: Note 1: Impairment variance of -194% is distorted by a near-zero 2024 base, refer to absolute figures for context. | B25: Note 2: PBT -175% variance reflects recovery from ₦221.6bn net loss in 2024 to ₦166.8bn net profit in 2025, a positive outcome despite the negative percentage displayed.
A26: Driver | B26: Impact on Profitability | C26: Figures
A27: Revenue Growth | B27: Positive | C27: ₦249bn
A28: Gross Margin Expansion | B28: Positive | C28: ₦130bn
A29: Lower Finance Costs | B29: Strong Positive | C29: ₦331bn (largest driver)
A30: Operating Profit Growth | B30: Positive | C30: ₦64bn
A31: Tax Expense | B31: Negative | C31: Partial offset

Sheet Assumption and Drivers
A1: Financial Drivers | B1: 3 Year Baseline | C1: Base Case | D1: Optimistic Case | E1: Worst Case
A2: Line Item Driver | B2: Past Performance | C2: Most Likely | D2: Upside OutLook | E2: Downside Volatility
A3: Revenue Growth Rate | B3: =AVERAGE('Historical Variance Analysis'!F2, 'Historical Variance Analysis'!H2) -> 0.50606615 | C3: 0.18 | D3: 0.25 | E3: 0.08
A4: Gross Margin % | B4: =AVERAGE('Historical Variance Analysis'!B5, 'Historical Variance Analysis'!C5, 'Historical Variance Analysis'!D5) -> 0.35911978 | C4: 0.37 | D4: 0.39 | E4: 0.31
A5: Marketing Expenses (% of Revenue) | B5: =AVERAGE(ABS('Historical Variance Analysis'!B7/'Historical Variance Analysis'!B2), ABS('Historical Variance Analysis'!C7/'Historical Variance Analysis'!C2), ABS('Historical Variance Analysis'!D7/'Historical Variance Analysis'!D2)) -> 0.12672389 | C5: 0.12 | D5: 0.115 | E5: 0.135
A6: Administrative Expenses (% of Revenue) | B6: =AVERAGE(ABS('Historical Variance Analysis'!B8/'Historical Variance Analysis'!B2), ABS('Historical Variance Analysis'!C8/'Historical Variance Analysis'!C2), ABS('Historical Variance Analysis'!D8/'Historical Variance Analysis'!D2)) -> 0.037295588 | C6: 0.04 | D6: 0.035 | E6: 0.05
A7: Net Finance Costs (Absolute ₦ Billions) | B7: =AVERAGE('Historical Variance Analysis'!B14, 'Historical Variance Analysis'!C14, 'Historical Variance Analysis'!D14)/1000000 -> -225.27125 | C7: -60 | D7: -40 | E7: -150
A8: Income Tax Rate (%) | B8: =AVERAGE(ABS('Historical Variance Analysis'!B16/'Historical Variance Analysis'!B14), ABS('Historical Variance Analysis'!C16/'Historical Variance Analysis'!C14)) -> 0.60174019 | C8: 0.32 | D8: 0.32 | E8: 0.35
A10: Select Active Scenario: | B10: Base Case
A12: Active Revenue Growth | B12: =INDEX($C$3:$E$3, MATCH($B$10, $C$1:$E$1, 0)) -> 0.18
A13: Active Gross Margin | B13: =INDEX($C$4:$E$4, MATCH($B$10, $C$1:$E$1, 0)) -> 0.37
A14: Active Marketing Exp | B14: =INDEX($C$5:$E$5, MATCH($B$10, $C$1:$E$1, 0)) -> 0.12
A15: Active Admin Exp | B15: =INDEX($C$6:$E$6, MATCH($B$10, $C$1:$E$1, 0)) -> 0.04
A16: Active Finance Costs | B16: {=_xlfn.IFS($B$10="Base Case", C7, $B$10="Optimistic Case", D7, $B$10="Worst Case", E7)} -> -60
A17: Active Tax Rate | B17: =INDEX($C$8:$E$8, MATCH($B$10, $C$1:$E$1, 0)) -> 0.32
A19: Baseline distorted by tax credits in loss years 2023-2024. Forward rate based on 2025 effective rate of 37%."

Sheet Table017
A1: Column1 | B1: Column4
A2: Revenue | B2: 326126755
A3: Cost of sales | B3: -194068808
A4: Gross profit | B4: 132057947
A5: Other income | B5: 240957
A6: Marketing and distribution expenses | B6: -43957358
A7: Administrative expenses | B7: -12880049
A8: Impairment (loss) /write-back on financial assets | B8: -29714
A9: Operating Expense
A10: Operating Profit | B10: 75431783
A11: Finance income | B11: 15261936
A12: Finance costs | B12: -16922810
A13: Net Finance Cost | B13: -1660874
A14: Profit/(Loss) Before Tax | B14: 73770909
A15: Income Tax Expense | B15: -34773050
A16: Net Profit After Tax | B16: 38997859
A17: Profit for the period is attributable to:
A18: Owners of the Company | B18: 38997859
A19: Earnings per share
A20: Basic earnings per share | B20: 49
A21: Diluted earnings | B21: 49

Sheet 2026 Rolling Forecast 
A1: Line Item (Figures in ₦ Billions) | B1: Q1 2026 Actual | C1: Q2 - Q4 2026 Forecast | D1: Full Year 2026 Target
A2: Income Statement Projections | B2: 3M Actual Anchor | C2: 9F Projections | D2: Estimated FY2026
A3: Revenue | B3: =326126755/1000000 -> 326.12676 | C3: ='Historical Variance Analysis'!B2/1000000/4*3*(1+'Assumption and Drivers'!$B$12) -> 1068.8792 | D3: =B3+C3 -> 1395.0059
A4: Cost of Sales | B4: =-194068808/1000000 -> -194.06881 | C4: =C5 - C3 -> -673.39388 | D4: =B4+C4 -> -867.46269
A5: Gross Profit | B5: =132057947/1000000 -> 132.05795 | C5: =C3 * 'Assumption and Drivers'!$B$13 -> 395.4853 | D5: =B5 + C5 -> 527.54324
A6: Operating Expenses | B6: =-56626164/1000000 -> -56.626164 | C6: =-C3 * ('Assumption and Drivers'!$B$14 + 'Assumption and Drivers'!$B$15) -> -171.02067 | D6: =B6+C6 -> -227.64683
A7: Operating Profit | B7: =75431783/1000000 -> 75.431783 | C7: =SUM(C5:C6) -> 224.46463 | D7: =B7+C7 -> 299.89641
A8: Net Finance Cost | B8: =-1660874/1000000 -> -1.660874 | C8: =D8 - B8 -> -58.339126 | D8: ='Assumption and Drivers'!$B$16 -> -60
A9: Profit/(Loss) Before Tax | B9: =73770909/1000000 -> 73.770909 | C9: =C7+C8 -> 166.1255 | D9: =B9+C9 -> 239.89641
A10: Income Tax Expense | B10: =-34773050/1000000 -> -34.77305 | C10: {=-_xlfn.IFS(C9>0, C9 * 'Assumption and Drivers'!$B$17, C9<=0, 0)} -> -53.16016 | D10: =B10+C10 -> -87.93321
A11: Net Profit After Tax | B11: =38997859/1000000 -> 38.997859 | C11: =C9+C10 -> 112.96534 | D11: =B11+C11 -> 151.9632
A12: Gross Profit Margin% | B12: =B5/B3 -> 0.40492828 | C12: =C5/C3 -> 0.37 | D12: =D5/D3 -> 0.37816559
A13: Operating Profit Margin % | B13: =B7/B3 -> 0.23129591 | C13: =C7/C3 -> 0.21 | D13: =D7/D3 -> 0.21497859
A14: Net Profit Margin % | B14: =B11/B3 -> 0.11957884 | C14: =C11/C3 -> 0.10568579 | D14: =D11/D3 -> 0.10893373

Sheet Scenario Analysis Dashboard
A1: Metric (in ₦ Billions) | B1: 2023 Actual | C1: 2024 Actual | D1: 2025 Actual | E1: 2026 Base Case
A2: Total Revenue | B2: 547118754 | C2: 958814739 | D2: 1207773081 | E2: ='2026 Rolling Forecast '!D3*1000000 -> 1.3950059e+09
A3: Net Finance Costs | B3: =_xlfn.XLOOKUP(A3, Append1!A:A, Append1!B:B,0) -> -227813025 | C3: -389464811 | D3: -58535900 | E3: ='2026 Rolling Forecast '!D8*1000000 -> -60000000
A4: Net Profit After Tax | B4: -79473781 | C4: -164595022 | D4: 104966001 | E4: ='2026 Rolling Forecast '!D11*1000000 -> 1.519632e+08
